{
  "uid": 1996612,
  "latestName": "AlexanToNY",
  "knownNames": [
    "AlexanToNY"
  ],
  "history": {
    "2026-05-28": {
      "TakenAtUtc": "2026-05-28T23:00:31.2607049Z",
      "Flat": {
        "effRating": "6284.8349609375",
        "nickName": "AlexanToNY",
        "prestigeBonus": "0.45",
        "uid": "1996612",
        "accountRank": "14",
        "pve.gamePlayed": "1784",
        "pve.unlimPve_playerAttackLevel": "15",
        "pve.unlimPve_playerDefenceLevel": "16",
        "pve.unlimPve_missionLevels.planet_war_waves_T1": "19",
        "pve.unlimPve_missionLevels.bigship_building_easy": "7",
        "pve.unlimPve_missionLevels.capture_repairbase_t1": "7",
        "pve.unlimPve_missionLevels.nalnifan_lumen_waves_T1": "19",
        "pve.unlimPve_missionLevels.pve_frozen_station_t2": "6",
        "pve.unlimPve_missionLevels.asteroid_building_t1": "4",
        "pve.unlimPve_missionLevels.pve_jericho_base_t2": "5",
        "pve.unlimPve_missionLevels.bigship_building_2_easy": "8",
        "pve.unlimPve_missionLevels.pve_empfrontier_waves_T1": "3",
        "pve.unlimPve_missionLevels.loot_geostation_normal": "3",
        "pve.unlimPve_missionLevels.piratebay_hard": "2",
        "pve.unlimPve_missionLevels.magnificent_seven": "3",
        "pve.wavePve_maxWave": "12",
        "pvp.gamePlayed": "490",
        "pvp.gameWin": "227",
        "pvp.totalAssists": "2401",
        "pvp.totalBattleTime": "185144052",
        "pvp.totalDeath": "803",
        "pvp.totalDmgDone": "73154703.866333",
        "pvp.totalHealingDone": "12140258.135864",
        "pvp.totalKill": "911",
        "pvp.totalVpDmgDone": "126.55975341797",
        "coop.gameWin": "54",
        "coop.gamePlayed": "56",
        "coop.totalBattleTime": "19898130",
        "openWorld.karma": "23281",
        "clan.name": "Fowler Defence",
        "clan.tag": "hDEF",
        "clan.cid": "1534",
        "clan.pvpRating": "7557",
        "clan.pveRating": "235174"
      }
    },
    "2026-05-29": {
      "TakenAtUtc": "2026-05-29T23:00:30.4497211Z",
      "Flat": {
        "effRating": "6284.8349609375",
        "nickName": "AlexanToNY",
        "prestigeBonus": "0.45",
        "uid": "1996612",
        "accountRank": "14",
        "pve.gamePlayed": "1784",
        "pve.unlimPve_playerAttackLevel": "15",
        "pve.unlimPve_playerDefenceLevel": "16",
        "pve.unlimPve_missionLevels.planet_war_waves_T1": "19",
        "pve.unlimPve_missionLevels.bigship_building_easy": "7",
        "pve.unlimPve_missionLevels.capture_repairbase_t1": "7",
        "pve.unlimPve_missionLevels.nalnifan_lumen_waves_T1": "19",
        "pve.unlimPve_missionLevels.pve_frozen_station_t2": "6",
        "pve.unlimPve_missionLevels.asteroid_building_t1": "4",
        "pve.unlimPve_missionLevels.pve_jericho_base_t2": "5",
        "pve.unlimPve_missionLevels.bigship_building_2_easy": "8",
        "pve.unlimPve_missionLevels.pve_empfrontier_waves_T1": "3",
        "pve.unlimPve_missionLevels.loot_geostation_normal": "3",
        "pve.unlimPve_missionLevels.piratebay_hard": "2",
        "pve.unlimPve_missionLevels.magnificent_seven": "3",
        "pve.wavePve_maxWave": "12",
        "pvp.gamePlayed": "490",
        "pvp.gameWin": "227",
        "pvp.totalAssists": "2401",
        "pvp.totalBattleTime": "185144052",
        "pvp.totalDeath": "803",
        "pvp.totalDmgDone": "73154703.866333",
        "pvp.totalHealingDone": "12140258.135864",
        "pvp.totalKill": "911",
        "pvp.totalVpDmgDone": "126.55975341797",
        "coop.gameWin": "54",
        "coop.gamePlayed": "56",
        "coop.totalBattleTime": "19898130",
        "openWorld.karma": "23281",
        "clan.name": "Fowler Defence",
        "clan.tag": "hDEF",
        "clan.cid": "1534",
        "clan.pvpRating": "7425",
        "clan.pveRating": "211681"
      }
    },
    "2026-05-30": {
      "TakenAtUtc": "2026-05-30T23:00:42.8016923Z",
      "Flat": {
        "effRating": "6284.8349609375",
        "nickName": "AlexanToNY",
        "prestigeBonus": "0.45",
        "uid": "1996612",
        "accountRank": "14",
        "pve.gamePlayed": "1784",
        "pve.unlimPve_playerAttackLevel": "15",
        "pve.unlimPve_playerDefenceLevel": "16",
        "pve.unlimPve_missionLevels.planet_war_waves_T1": "19",
        "pve.unlimPve_missionLevels.bigship_building_easy": "7",
        "pve.unlimPve_missionLevels.capture_repairbase_t1": "7",
        "pve.unlimPve_missionLevels.nalnifan_lumen_waves_T1": "19",
        "pve.unlimPve_missionLevels.pve_frozen_station_t2": "6",
        "pve.unlimPve_missionLevels.asteroid_building_t1": "4",
        "pve.unlimPve_missionLevels.pve_jericho_base_t2": "5",
        "pve.unlimPve_missionLevels.bigship_building_2_easy": "8",
        "pve.unlimPve_missionLevels.pve_empfrontier_waves_T1": "3",
        "pve.unlimPve_missionLevels.loot_geostation_normal": "3",
        "pve.unlimPve_missionLevels.piratebay_hard": "2",
        "pve.unlimPve_missionLevels.magnificent_seven": "3",
        "pve.wavePve_maxWave": "12",
        "pvp.gamePlayed": "490",
        "pvp.gameWin": "227",
        "pvp.totalAssists": "2401",
        "pvp.totalBattleTime": "185144052",
        "pvp.totalDeath": "803",
        "pvp.totalDmgDone": "73154703.866333",
        "pvp.totalHealingDone": "12140258.135864",
        "pvp.totalKill": "911",
        "pvp.totalVpDmgDone": "126.55975341797",
        "coop.gameWin": "54",
        "coop.gamePlayed": "56",
        "coop.totalBattleTime": "19898130",
        "openWorld.karma": "23281",
        "clan.name": "Fowler Defence",
        "clan.tag": "hDEF",
        "clan.cid": "1534",
        "clan.pvpRating": "7737",
        "clan.pveRating": "299198"
      }
    },
    "2026-05-31": {
      "TakenAtUtc": "2026-05-31T23:00:32.248475Z",
      "Flat": {
        "effRating": "6284.8349609375",
        "nickName": "AlexanToNY",
        "prestigeBonus": "0.45",
        "uid": "1996612",
        "accountRank": "14",
        "pve.gamePlayed": "1784",
        "pve.unlimPve_playerAttackLevel": "15",
        "pve.unlimPve_playerDefenceLevel": "16",
        "pve.unlimPve_missionLevels.planet_war_waves_T1": "19",
        "pve.unlimPve_missionLevels.bigship_building_easy": "7",
        "pve.unlimPve_missionLevels.capture_repairbase_t1": "7",
        "pve.unlimPve_missionLevels.nalnifan_lumen_waves_T1": "19",
        "pve.unlimPve_missionLevels.pve_frozen_station_t2": "6",
        "pve.unlimPve_missionLevels.asteroid_building_t1": "4",
        "pve.unlimPve_missionLevels.pve_jericho_base_t2": "5",
        "pve.unlimPve_missionLevels.bigship_building_2_easy": "8",
        "pve.unlimPve_missionLevels.pve_empfrontier_waves_T1": "3",
        "pve.unlimPve_missionLevels.loot_geostation_normal": "3",
        "pve.unlimPve_missionLevels.piratebay_hard": "2",
        "pve.unlimPve_missionLevels.magnificent_seven": "3",
        "pve.wavePve_maxWave": "12",
        "pvp.gamePlayed": "490",
        "pvp.gameWin": "227",
        "pvp.totalAssists": "2401",
        "pvp.totalBattleTime": "185144052",
        "pvp.totalDeath": "803",
        "pvp.totalDmgDone": "73154703.866333",
        "pvp.totalHealingDone": "12140258.135864",
        "pvp.totalKill": "911",
        "pvp.totalVpDmgDone": "126.55975341797",
        "coop.gameWin": "54",
        "coop.gamePlayed": "56",
        "coop.totalBattleTime": "19898130",
        "openWorld.karma": "23281",
        "clan.name": "Fowler Defence",
        "clan.tag": "hDEF",
        "clan.cid": "1534",
        "clan.pvpRating": "7657",
        "clan.pveRating": "265799"
      }
    },
    "2026-06-01": {
      "TakenAtUtc": "2026-06-01T23:00:30.4289252Z",
      "Flat": {
        "effRating": "6284.8349609375",
        "nickName": "AlexanToNY",
        "prestigeBonus": "0.45",
        "uid": "1996612",
        "accountRank": "14",
        "pve.gamePlayed": "1784",
        "pve.unlimPve_playerAttackLevel": "15",
        "pve.unlimPve_playerDefenceLevel": "16",
        "pve.unlimPve_missionLevels.planet_war_waves_T1": "19",
        "pve.unlimPve_missionLevels.bigship_building_easy": "7",
        "pve.unlimPve_missionLevels.capture_repairbase_t1": "7",
        "pve.unlimPve_missionLevels.nalnifan_lumen_waves_T1": "19",
        "pve.unlimPve_missionLevels.pve_frozen_station_t2": "6",
        "pve.unlimPve_missionLevels.asteroid_building_t1": "4",
        "pve.unlimPve_missionLevels.pve_jericho_base_t2": "5",
        "pve.unlimPve_missionLevels.bigship_building_2_easy": "8",
        "pve.unlimPve_missionLevels.pve_empfrontier_waves_T1": "3",
        "pve.unlimPve_missionLevels.loot_geostation_normal": "3",
        "pve.unlimPve_missionLevels.piratebay_hard": "2",
        "pve.unlimPve_missionLevels.magnificent_seven": "3",
        "pve.wavePve_maxWave": "12",
        "pvp.gamePlayed": "490",
        "pvp.gameWin": "227",
        "pvp.totalAssists": "2401",
        "pvp.totalBattleTime": "185144052",
        "pvp.totalDeath": "803",
        "pvp.totalDmgDone": "73154703.866333",
        "pvp.totalHealingDone": "12140258.135864",
        "pvp.totalKill": "911",
        "pvp.totalVpDmgDone": "126.55975341797",
        "coop.gameWin": "54",
        "coop.gamePlayed": "56",
        "coop.totalBattleTime": "19898130",
        "openWorld.karma": "23281",
        "clan.name": "Fowler Defence",
        "clan.tag": "hDEF",
        "clan.cid": "1534",
        "clan.pvpRating": "7976",
        "clan.pveRating": "212252"
      }
    },
    "2026-06-02": {
      "TakenAtUtc": "2026-06-02T23:00:33.3963647Z",
      "Flat": {
        "effRating": "6284.8349609375",
        "nickName": "AlexanToNY",
        "prestigeBonus": "0.45",
        "uid": "1996612",
        "accountRank": "14",
        "pve.gamePlayed": "1784",
        "pve.unlimPve_playerAttackLevel": "15",
        "pve.unlimPve_playerDefenceLevel": "16",
        "pve.unlimPve_missionLevels.planet_war_waves_T1": "19",
        "pve.unlimPve_missionLevels.bigship_building_easy": "7",
        "pve.unlimPve_missionLevels.capture_repairbase_t1": "7",
        "pve.unlimPve_missionLevels.nalnifan_lumen_waves_T1": "19",
        "pve.unlimPve_missionLevels.pve_frozen_station_t2": "6",
        "pve.unlimPve_missionLevels.asteroid_building_t1": "4",
        "pve.unlimPve_missionLevels.pve_jericho_base_t2": "5",
        "pve.unlimPve_missionLevels.bigship_building_2_easy": "8",
        "pve.unlimPve_missionLevels.pve_empfrontier_waves_T1": "3",
        "pve.unlimPve_missionLevels.loot_geostation_normal": "3",
        "pve.unlimPve_missionLevels.piratebay_hard": "2",
        "pve.unlimPve_missionLevels.magnificent_seven": "3",
        "pve.wavePve_maxWave": "12",
        "pvp.gamePlayed": "490",
        "pvp.gameWin": "227",
        "pvp.totalAssists": "2401",
        "pvp.totalBattleTime": "185144052",
        "pvp.totalDeath": "803",
        "pvp.totalDmgDone": "73154703.866333",
        "pvp.totalHealingDone": "12140258.135864",
        "pvp.totalKill": "911",
        "pvp.totalVpDmgDone": "126.55975341797",
        "coop.gameWin": "54",
        "coop.gamePlayed": "56",
        "coop.totalBattleTime": "19898130",
        "openWorld.karma": "23281",
        "clan.name": "Fowler Defence",
        "clan.tag": "hDEF",
        "clan.cid": "1534",
        "clan.pvpRating": "7304",
        "clan.pveRating": "197783"
      }
    },
    "2026-06-03": {
      "TakenAtUtc": "2026-06-03T23:00:36.8787344Z",
      "Flat": {
        "effRating": "6284.8349609375",
        "nickName": "AlexanToNY",
        "prestigeBonus": "0.45",
        "uid": "1996612",
        "accountRank": "14",
        "pve.gamePlayed": "1784",
        "pve.unlimPve_playerAttackLevel": "15",
        "pve.unlimPve_playerDefenceLevel": "16",
        "pve.unlimPve_missionLevels.planet_war_waves_T1": "19",
        "pve.unlimPve_missionLevels.bigship_building_easy": "7",
        "pve.unlimPve_missionLevels.capture_repairbase_t1": "7",
        "pve.unlimPve_missionLevels.nalnifan_lumen_waves_T1": "19",
        "pve.unlimPve_missionLevels.pve_frozen_station_t2": "6",
        "pve.unlimPve_missionLevels.asteroid_building_t1": "4",
        "pve.unlimPve_missionLevels.pve_jericho_base_t2": "5",
        "pve.unlimPve_missionLevels.bigship_building_2_easy": "8",
        "pve.unlimPve_missionLevels.pve_empfrontier_waves_T1": "3",
        "pve.unlimPve_missionLevels.loot_geostation_normal": "3",
        "pve.unlimPve_missionLevels.piratebay_hard": "2",
        "pve.unlimPve_missionLevels.magnificent_seven": "3",
        "pve.wavePve_maxWave": "12",
        "pvp.gamePlayed": "490",
        "pvp.gameWin": "227",
        "pvp.totalAssists": "2401",
        "pvp.totalBattleTime": "185144052",
        "pvp.totalDeath": "803",
        "pvp.totalDmgDone": "73154703.866333",
        "pvp.totalHealingDone": "12140258.135864",
        "pvp.totalKill": "911",
        "pvp.totalVpDmgDone": "126.55975341797",
        "coop.gameWin": "54",
        "coop.gamePlayed": "56",
        "coop.totalBattleTime": "19898130",
        "openWorld.karma": "23281",
        "clan.name": "Fowler Defence",
        "clan.tag": "hDEF",
        "clan.cid": "1534",
        "clan.pvpRating": "8089",
        "clan.pveRating": "159110"
      }
    },
    "2026-06-04": {
      "TakenAtUtc": "2026-06-04T23:00:33.7272523Z",
      "Flat": {
        "effRating": "6284.8349609375",
        "nickName": "AlexanToNY",
        "prestigeBonus": "0.45",
        "uid": "1996612",
        "accountRank": "14",
        "pve.gamePlayed": "1784",
        "pve.unlimPve_playerAttackLevel": "15",
        "pve.unlimPve_playerDefenceLevel": "16",
        "pve.unlimPve_missionLevels.planet_war_waves_T1": "19",
        "pve.unlimPve_missionLevels.bigship_building_easy": "7",
        "pve.unlimPve_missionLevels.capture_repairbase_t1": "7",
        "pve.unlimPve_missionLevels.nalnifan_lumen_waves_T1": "19",
        "pve.unlimPve_missionLevels.pve_frozen_station_t2": "6",
        "pve.unlimPve_missionLevels.asteroid_building_t1": "4",
        "pve.unlimPve_missionLevels.pve_jericho_base_t2": "5",
        "pve.unlimPve_missionLevels.bigship_building_2_easy": "8",
        "pve.unlimPve_missionLevels.pve_empfrontier_waves_T1": "3",
        "pve.unlimPve_missionLevels.loot_geostation_normal": "3",
        "pve.unlimPve_missionLevels.piratebay_hard": "2",
        "pve.unlimPve_missionLevels.magnificent_seven": "3",
        "pve.wavePve_maxWave": "12",
        "pvp.gamePlayed": "490",
        "pvp.gameWin": "227",
        "pvp.totalAssists": "2401",
        "pvp.totalBattleTime": "185144052",
        "pvp.totalDeath": "803",
        "pvp.totalDmgDone": "73154703.866333",
        "pvp.totalHealingDone": "12140258.135864",
        "pvp.totalKill": "911",
        "pvp.totalVpDmgDone": "126.55975341797",
        "coop.gameWin": "54",
        "coop.gamePlayed": "56",
        "coop.totalBattleTime": "19898130",
        "openWorld.karma": "23281",
        "clan.name": "Weird Name",
        "clan.tag": "WHEN",
        "clan.cid": "1534",
        "clan.pvpRating": "7649",
        "clan.pveRating": "131600"
      }
    },
    "2026-06-05": {
      "TakenAtUtc": "2026-06-05T23:00:32.9874557Z",
      "Flat": {
        "effRating": "6284.8349609375",
        "nickName": "AlexanToNY",
        "prestigeBonus": "0.45",
        "uid": "1996612",
        "accountRank": "14",
        "pve.gamePlayed": "1784",
        "pve.unlimPve_playerAttackLevel": "15",
        "pve.unlimPve_playerDefenceLevel": "16",
        "pve.unlimPve_missionLevels.planet_war_waves_T1": "19",
        "pve.unlimPve_missionLevels.bigship_building_easy": "7",
        "pve.unlimPve_missionLevels.capture_repairbase_t1": "7",
        "pve.unlimPve_missionLevels.nalnifan_lumen_waves_T1": "19",
        "pve.unlimPve_missionLevels.pve_frozen_station_t2": "6",
        "pve.unlimPve_missionLevels.asteroid_building_t1": "4",
        "pve.unlimPve_missionLevels.pve_jericho_base_t2": "5",
        "pve.unlimPve_missionLevels.bigship_building_2_easy": "8",
        "pve.unlimPve_missionLevels.pve_empfrontier_waves_T1": "3",
        "pve.unlimPve_missionLevels.loot_geostation_normal": "3",
        "pve.unlimPve_missionLevels.piratebay_hard": "2",
        "pve.unlimPve_missionLevels.magnificent_seven": "3",
        "pve.wavePve_maxWave": "12",
        "pvp.gamePlayed": "490",
        "pvp.gameWin": "227",
        "pvp.totalAssists": "2401",
        "pvp.totalBattleTime": "185144052",
        "pvp.totalDeath": "803",
        "pvp.totalDmgDone": "73154703.866333",
        "pvp.totalHealingDone": "12140258.135864",
        "pvp.totalKill": "911",
        "pvp.totalVpDmgDone": "126.55975341797",
        "coop.gameWin": "54",
        "coop.gamePlayed": "56",
        "coop.totalBattleTime": "19898130",
        "openWorld.karma": "23281",
        "clan.name": "Stu",
        "clan.tag": "Pid",
        "clan.cid": "1534",
        "clan.pvpRating": "8025",
        "clan.pveRating": "204156"
      }
    },
    "2026-06-06": {
      "TakenAtUtc": "2026-06-06T23:00:33.3699465Z",
      "Flat": {
        "effRating": "6284.8349609375",
        "nickName": "AlexanToNY",
        "prestigeBonus": "0.45",
        "uid": "1996612",
        "accountRank": "14",
        "pve.gamePlayed": "1784",
        "pve.unlimPve_playerAttackLevel": "15",
        "pve.unlimPve_playerDefenceLevel": "16",
        "pve.unlimPve_missionLevels.planet_war_waves_T1": "19",
        "pve.unlimPve_missionLevels.bigship_building_easy": "7",
        "pve.unlimPve_missionLevels.capture_repairbase_t1": "7",
        "pve.unlimPve_missionLevels.nalnifan_lumen_waves_T1": "19",
        "pve.unlimPve_missionLevels.pve_frozen_station_t2": "6",
        "pve.unlimPve_missionLevels.asteroid_building_t1": "4",
        "pve.unlimPve_missionLevels.pve_jericho_base_t2": "5",
        "pve.unlimPve_missionLevels.bigship_building_2_easy": "8",
        "pve.unlimPve_missionLevels.pve_empfrontier_waves_T1": "3",
        "pve.unlimPve_missionLevels.loot_geostation_normal": "3",
        "pve.unlimPve_missionLevels.piratebay_hard": "2",
        "pve.unlimPve_missionLevels.magnificent_seven": "3",
        "pve.wavePve_maxWave": "12",
        "pvp.gamePlayed": "490",
        "pvp.gameWin": "227",
        "pvp.totalAssists": "2401",
        "pvp.totalBattleTime": "185144052",
        "pvp.totalDeath": "803",
        "pvp.totalDmgDone": "73154703.866333",
        "pvp.totalHealingDone": "12140258.135864",
        "pvp.totalKill": "911",
        "pvp.totalVpDmgDone": "126.55975341797",
        "coop.gameWin": "54",
        "coop.gamePlayed": "56",
        "coop.totalBattleTime": "19898130",
        "openWorld.karma": "23281",
        "clan.name": "Stu",
        "clan.tag": "Pid",
        "clan.cid": "1534",
        "clan.pvpRating": "8153",
        "clan.pveRating": "231239"
      }
    },
    "2026-06-07": {
      "TakenAtUtc": "2026-06-07T23:00:33.3396787Z",
      "Flat": {
        "effRating": "6284.8349609375",
        "nickName": "AlexanToNY",
        "prestigeBonus": "0.45",
        "uid": "1996612",
        "accountRank": "14",
        "pve.gamePlayed": "1784",
        "pve.unlimPve_playerAttackLevel": "15",
        "pve.unlimPve_playerDefenceLevel": "16",
        "pve.unlimPve_missionLevels.planet_war_waves_T1": "19",
        "pve.unlimPve_missionLevels.bigship_building_easy": "7",
        "pve.unlimPve_missionLevels.capture_repairbase_t1": "7",
        "pve.unlimPve_missionLevels.nalnifan_lumen_waves_T1": "19",
        "pve.unlimPve_missionLevels.pve_frozen_station_t2": "6",
        "pve.unlimPve_missionLevels.asteroid_building_t1": "4",
        "pve.unlimPve_missionLevels.pve_jericho_base_t2": "5",
        "pve.unlimPve_missionLevels.bigship_building_2_easy": "8",
        "pve.unlimPve_missionLevels.pve_empfrontier_waves_T1": "3",
        "pve.unlimPve_missionLevels.loot_geostation_normal": "3",
        "pve.unlimPve_missionLevels.piratebay_hard": "2",
        "pve.unlimPve_missionLevels.magnificent_seven": "3",
        "pve.wavePve_maxWave": "12",
        "pvp.gamePlayed": "490",
        "pvp.gameWin": "227",
        "pvp.totalAssists": "2401",
        "pvp.totalBattleTime": "185144052",
        "pvp.totalDeath": "803",
        "pvp.totalDmgDone": "73154703.866333",
        "pvp.totalHealingDone": "12140258.135864",
        "pvp.totalKill": "911",
        "pvp.totalVpDmgDone": "126.55975341797",
        "coop.gameWin": "54",
        "coop.gamePlayed": "56",
        "coop.totalBattleTime": "19898130",
        "openWorld.karma": "23281",
        "clan.name": "Happy Bday",
        "clan.tag": "TEKNO",
        "clan.cid": "1534",
        "clan.pvpRating": "8283",
        "clan.pveRating": "181666"
      }
    },
    "2026-06-08": {
      "TakenAtUtc": "2026-06-08T23:00:35.0440101Z",
      "Flat": {
        "effRating": "6284.8349609375",
        "nickName": "AlexanToNY",
        "prestigeBonus": "0.45",
        "uid": "1996612",
        "accountRank": "14",
        "pve.gamePlayed": "1784",
        "pve.unlimPve_playerAttackLevel": "15",
        "pve.unlimPve_playerDefenceLevel": "16",
        "pve.unlimPve_missionLevels.planet_war_waves_T1": "19",
        "pve.unlimPve_missionLevels.bigship_building_easy": "7",
        "pve.unlimPve_missionLevels.capture_repairbase_t1": "7",
        "pve.unlimPve_missionLevels.nalnifan_lumen_waves_T1": "19",
        "pve.unlimPve_missionLevels.pve_frozen_station_t2": "6",
        "pve.unlimPve_missionLevels.asteroid_building_t1": "4",
        "pve.unlimPve_missionLevels.pve_jericho_base_t2": "5",
        "pve.unlimPve_missionLevels.bigship_building_2_easy": "8",
        "pve.unlimPve_missionLevels.pve_empfrontier_waves_T1": "3",
        "pve.unlimPve_missionLevels.loot_geostation_normal": "3",
        "pve.unlimPve_missionLevels.piratebay_hard": "2",
        "pve.unlimPve_missionLevels.magnificent_seven": "3",
        "pve.wavePve_maxWave": "12",
        "pvp.gamePlayed": "490",
        "pvp.gameWin": "227",
        "pvp.totalAssists": "2401",
        "pvp.totalBattleTime": "185144052",
        "pvp.totalDeath": "803",
        "pvp.totalDmgDone": "73154703.866333",
        "pvp.totalHealingDone": "12140258.135864",
        "pvp.totalKill": "911",
        "pvp.totalVpDmgDone": "126.55975341797",
        "coop.gameWin": "54",
        "coop.gamePlayed": "56",
        "coop.totalBattleTime": "19898130",
        "openWorld.karma": "23281",
        "clan.name": "Happy Bday",
        "clan.tag": "TEKNO",
        "clan.cid": "1534",
        "clan.pvpRating": "8178",
        "clan.pveRating": "149082"
      }
    },
    "2026-06-09": {
      "TakenAtUtc": "2026-06-09T23:00:36.4412493Z",
      "Flat": {
        "effRating": "6284.8349609375",
        "nickName": "AlexanToNY",
        "prestigeBonus": "0.45",
        "uid": "1996612",
        "accountRank": "14",
        "pve.gamePlayed": "1784",
        "pve.unlimPve_playerAttackLevel": "15",
        "pve.unlimPve_playerDefenceLevel": "16",
        "pve.unlimPve_missionLevels.planet_war_waves_T1": "19",
        "pve.unlimPve_missionLevels.bigship_building_easy": "7",
        "pve.unlimPve_missionLevels.capture_repairbase_t1": "7",
        "pve.unlimPve_missionLevels.nalnifan_lumen_waves_T1": "19",
        "pve.unlimPve_missionLevels.pve_frozen_station_t2": "6",
        "pve.unlimPve_missionLevels.asteroid_building_t1": "4",
        "pve.unlimPve_missionLevels.pve_jericho_base_t2": "5",
        "pve.unlimPve_missionLevels.bigship_building_2_easy": "8",
        "pve.unlimPve_missionLevels.pve_empfrontier_waves_T1": "3",
        "pve.unlimPve_missionLevels.loot_geostation_normal": "3",
        "pve.unlimPve_missionLevels.piratebay_hard": "2",
        "pve.unlimPve_missionLevels.magnificent_seven": "3",
        "pve.wavePve_maxWave": "12",
        "pvp.gamePlayed": "490",
        "pvp.gameWin": "227",
        "pvp.totalAssists": "2401",
        "pvp.totalBattleTime": "185144052",
        "pvp.totalDeath": "803",
        "pvp.totalDmgDone": "73154703.866333",
        "pvp.totalHealingDone": "12140258.135864",
        "pvp.totalKill": "911",
        "pvp.totalVpDmgDone": "126.55975341797",
        "coop.gameWin": "54",
        "coop.gamePlayed": "56",
        "coop.totalBattleTime": "19898130",
        "openWorld.karma": "23281",
        "clan.name": "Happy Bday",
        "clan.tag": "TEKNO",
        "clan.cid": "1534",
        "clan.pvpRating": "10273",
        "clan.pveRating": "134777"
      }
    },
    "2026-06-10": {
      "TakenAtUtc": "2026-06-10T23:00:33.2916111Z",
      "Flat": {
        "effRating": "6284.8349609375",
        "nickName": "AlexanToNY",
        "prestigeBonus": "0.45",
        "uid": "1996612",
        "accountRank": "14",
        "pve.gamePlayed": "1784",
        "pve.unlimPve_playerAttackLevel": "15",
        "pve.unlimPve_playerDefenceLevel": "16",
        "pve.unlimPve_missionLevels.planet_war_waves_T1": "19",
        "pve.unlimPve_missionLevels.bigship_building_easy": "7",
        "pve.unlimPve_missionLevels.capture_repairbase_t1": "7",
        "pve.unlimPve_missionLevels.nalnifan_lumen_waves_T1": "19",
        "pve.unlimPve_missionLevels.pve_frozen_station_t2": "6",
        "pve.unlimPve_missionLevels.asteroid_building_t1": "4",
        "pve.unlimPve_missionLevels.pve_jericho_base_t2": "5",
        "pve.unlimPve_missionLevels.bigship_building_2_easy": "8",
        "pve.unlimPve_missionLevels.pve_empfrontier_waves_T1": "3",
        "pve.unlimPve_missionLevels.loot_geostation_normal": "3",
        "pve.unlimPve_missionLevels.piratebay_hard": "2",
        "pve.unlimPve_missionLevels.magnificent_seven": "3",
        "pve.wavePve_maxWave": "12",
        "pvp.gamePlayed": "490",
        "pvp.gameWin": "227",
        "pvp.totalAssists": "2401",
        "pvp.totalBattleTime": "185144052",
        "pvp.totalDeath": "803",
        "pvp.totalDmgDone": "73154703.866333",
        "pvp.totalHealingDone": "12140258.135864",
        "pvp.totalKill": "911",
        "pvp.totalVpDmgDone": "126.55975341797",
        "coop.gameWin": "54",
        "coop.gamePlayed": "56",
        "coop.totalBattleTime": "19898130",
        "openWorld.karma": "23281",
        "clan.name": "Happy Bday",
        "clan.tag": "TEKNO",
        "clan.cid": "1534",
        "clan.pvpRating": "10674",
        "clan.pveRating": "115661"
      }
    },
    "2026-06-11": {
      "TakenAtUtc": "2026-06-11T23:00:34.8326831Z",
      "Flat": {
        "effRating": "6284.8349609375",
        "nickName": "AlexanToNY",
        "prestigeBonus": "0.45",
        "uid": "1996612",
        "accountRank": "14",
        "pve.gamePlayed": "1784",
        "pve.unlimPve_playerAttackLevel": "15",
        "pve.unlimPve_playerDefenceLevel": "16",
        "pve.unlimPve_missionLevels.planet_war_waves_T1": "19",
        "pve.unlimPve_missionLevels.bigship_building_easy": "7",
        "pve.unlimPve_missionLevels.capture_repairbase_t1": "7",
        "pve.unlimPve_missionLevels.nalnifan_lumen_waves_T1": "19",
        "pve.unlimPve_missionLevels.pve_frozen_station_t2": "6",
        "pve.unlimPve_missionLevels.asteroid_building_t1": "4",
        "pve.unlimPve_missionLevels.pve_jericho_base_t2": "5",
        "pve.unlimPve_missionLevels.bigship_building_2_easy": "8",
        "pve.unlimPve_missionLevels.pve_empfrontier_waves_T1": "3",
        "pve.unlimPve_missionLevels.loot_geostation_normal": "3",
        "pve.unlimPve_missionLevels.piratebay_hard": "2",
        "pve.unlimPve_missionLevels.magnificent_seven": "3",
        "pve.wavePve_maxWave": "12",
        "pvp.gamePlayed": "490",
        "pvp.gameWin": "227",
        "pvp.totalAssists": "2401",
        "pvp.totalBattleTime": "185144052",
        "pvp.totalDeath": "803",
        "pvp.totalDmgDone": "73154703.866333",
        "pvp.totalHealingDone": "12140258.135864",
        "pvp.totalKill": "911",
        "pvp.totalVpDmgDone": "126.55975341797",
        "coop.gameWin": "54",
        "coop.gamePlayed": "56",
        "coop.totalBattleTime": "19898130",
        "openWorld.karma": "23281",
        "clan.name": "Happy Bday",
        "clan.tag": "TEKNO",
        "clan.cid": "1534",
        "clan.pvpRating": "10899",
        "clan.pveRating": "97688"
      }
    },
    "2026-06-12": {
      "TakenAtUtc": "2026-06-12T23:00:33.1770332Z",
      "Flat": {
        "effRating": "6284.8349609375",
        "nickName": "AlexanToNY",
        "prestigeBonus": "0.45",
        "uid": "1996612",
        "accountRank": "14",
        "pve.gamePlayed": "1784",
        "pve.unlimPve_playerAttackLevel": "15",
        "pve.unlimPve_playerDefenceLevel": "16",
        "pve.unlimPve_missionLevels.planet_war_waves_T1": "19",
        "pve.unlimPve_missionLevels.bigship_building_easy": "7",
        "pve.unlimPve_missionLevels.capture_repairbase_t1": "7",
        "pve.unlimPve_missionLevels.nalnifan_lumen_waves_T1": "19",
        "pve.unlimPve_missionLevels.pve_frozen_station_t2": "6",
        "pve.unlimPve_missionLevels.asteroid_building_t1": "4",
        "pve.unlimPve_missionLevels.pve_jericho_base_t2": "5",
        "pve.unlimPve_missionLevels.bigship_building_2_easy": "8",
        "pve.unlimPve_missionLevels.pve_empfrontier_waves_T1": "3",
        "pve.unlimPve_missionLevels.loot_geostation_normal": "3",
        "pve.unlimPve_missionLevels.piratebay_hard": "2",
        "pve.unlimPve_missionLevels.magnificent_seven": "3",
        "pve.wavePve_maxWave": "12",
        "pvp.gamePlayed": "490",
        "pvp.gameWin": "227",
        "pvp.totalAssists": "2401",
        "pvp.totalBattleTime": "185144052",
        "pvp.totalDeath": "803",
        "pvp.totalDmgDone": "73154703.866333",
        "pvp.totalHealingDone": "12140258.135864",
        "pvp.totalKill": "911",
        "pvp.totalVpDmgDone": "126.55975341797",
        "coop.gameWin": "54",
        "coop.gamePlayed": "56",
        "coop.totalBattleTime": "19898130",
        "openWorld.karma": "23281",
        "clan.name": "Happy Bday",
        "clan.tag": "TEKNO",
        "clan.cid": "1534",
        "clan.pvpRating": "11600",
        "clan.pveRating": "340904"
      }
    },
    "2026-06-13": {
      "TakenAtUtc": "2026-06-13T23:00:33.9439303Z",
      "Flat": {
        "effRating": "6284.8349609375",
        "nickName": "AlexanToNY",
        "prestigeBonus": "0.45",
        "uid": "1996612",
        "accountRank": "14",
        "pve.gamePlayed": "1784",
        "pve.unlimPve_playerAttackLevel": "15",
        "pve.unlimPve_playerDefenceLevel": "16",
        "pve.unlimPve_missionLevels.planet_war_waves_T1": "19",
        "pve.unlimPve_missionLevels.bigship_building_easy": "7",
        "pve.unlimPve_missionLevels.capture_repairbase_t1": "7",
        "pve.unlimPve_missionLevels.nalnifan_lumen_waves_T1": "19",
        "pve.unlimPve_missionLevels.pve_frozen_station_t2": "6",
        "pve.unlimPve_missionLevels.asteroid_building_t1": "4",
        "pve.unlimPve_missionLevels.pve_jericho_base_t2": "5",
        "pve.unlimPve_missionLevels.bigship_building_2_easy": "8",
        "pve.unlimPve_missionLevels.pve_empfrontier_waves_T1": "3",
        "pve.unlimPve_missionLevels.loot_geostation_normal": "3",
        "pve.unlimPve_missionLevels.piratebay_hard": "2",
        "pve.unlimPve_missionLevels.magnificent_seven": "3",
        "pve.wavePve_maxWave": "12",
        "pvp.gamePlayed": "490",
        "pvp.gameWin": "227",
        "pvp.totalAssists": "2401",
        "pvp.totalBattleTime": "185144052",
        "pvp.totalDeath": "803",
        "pvp.totalDmgDone": "73154703.866333",
        "pvp.totalHealingDone": "12140258.135864",
        "pvp.totalKill": "911",
        "pvp.totalVpDmgDone": "126.55975341797",
        "coop.gameWin": "54",
        "coop.gamePlayed": "56",
        "coop.totalBattleTime": "19898130",
        "openWorld.karma": "23281",
        "clan.name": "Happy Bday",
        "clan.tag": "TEKNO",
        "clan.cid": "1534",
        "clan.pvpRating": "11628",
        "clan.pveRating": "401203"
      }
    },
    "2026-06-14": {
      "TakenAtUtc": "2026-06-14T23:00:30.6615918Z",
      "Flat": {
        "effRating": "6284.8349609375",
        "nickName": "AlexanToNY",
        "prestigeBonus": "0.45",
        "uid": "1996612",
        "accountRank": "14",
        "pve.gamePlayed": "1784",
        "pve.unlimPve_playerAttackLevel": "15",
        "pve.unlimPve_playerDefenceLevel": "16",
        "pve.unlimPve_missionLevels.planet_war_waves_T1": "19",
        "pve.unlimPve_missionLevels.bigship_building_easy": "7",
        "pve.unlimPve_missionLevels.capture_repairbase_t1": "7",
        "pve.unlimPve_missionLevels.nalnifan_lumen_waves_T1": "19",
        "pve.unlimPve_missionLevels.pve_frozen_station_t2": "6",
        "pve.unlimPve_missionLevels.asteroid_building_t1": "4",
        "pve.unlimPve_missionLevels.pve_jericho_base_t2": "5",
        "pve.unlimPve_missionLevels.bigship_building_2_easy": "8",
        "pve.unlimPve_missionLevels.pve_empfrontier_waves_T1": "3",
        "pve.unlimPve_missionLevels.loot_geostation_normal": "3",
        "pve.unlimPve_missionLevels.piratebay_hard": "2",
        "pve.unlimPve_missionLevels.magnificent_seven": "3",
        "pve.wavePve_maxWave": "12",
        "pvp.gamePlayed": "490",
        "pvp.gameWin": "227",
        "pvp.totalAssists": "2401",
        "pvp.totalBattleTime": "185144052",
        "pvp.totalDeath": "803",
        "pvp.totalDmgDone": "73154703.866333",
        "pvp.totalHealingDone": "12140258.135864",
        "pvp.totalKill": "911",
        "pvp.totalVpDmgDone": "126.55975341797",
        "coop.gameWin": "54",
        "coop.gamePlayed": "56",
        "coop.totalBattleTime": "19898130",
        "openWorld.karma": "23281",
        "clan.name": "Happy Bday",
        "clan.tag": "TEKNO",
        "clan.cid": "1534",
        "clan.pvpRating": "10902",
        "clan.pveRating": "320794"
      }
    },
    "2026-06-15": {
      "TakenAtUtc": "2026-06-15T23:00:36.4216777Z",
      "Flat": {
        "effRating": "6284.8349609375",
        "nickName": "AlexanToNY",
        "prestigeBonus": "0.45",
        "uid": "1996612",
        "accountRank": "14",
        "pve.gamePlayed": "1784",
        "pve.unlimPve_playerAttackLevel": "15",
        "pve.unlimPve_playerDefenceLevel": "16",
        "pve.unlimPve_missionLevels.planet_war_waves_T1": "19",
        "pve.unlimPve_missionLevels.bigship_building_easy": "7",
        "pve.unlimPve_missionLevels.capture_repairbase_t1": "7",
        "pve.unlimPve_missionLevels.nalnifan_lumen_waves_T1": "19",
        "pve.unlimPve_missionLevels.pve_frozen_station_t2": "6",
        "pve.unlimPve_missionLevels.asteroid_building_t1": "4",
        "pve.unlimPve_missionLevels.pve_jericho_base_t2": "5",
        "pve.unlimPve_missionLevels.bigship_building_2_easy": "8",
        "pve.unlimPve_missionLevels.pve_empfrontier_waves_T1": "3",
        "pve.unlimPve_missionLevels.loot_geostation_normal": "3",
        "pve.unlimPve_missionLevels.piratebay_hard": "2",
        "pve.unlimPve_missionLevels.magnificent_seven": "3",
        "pve.wavePve_maxWave": "12",
        "pvp.gamePlayed": "490",
        "pvp.gameWin": "227",
        "pvp.totalAssists": "2401",
        "pvp.totalBattleTime": "185144052",
        "pvp.totalDeath": "803",
        "pvp.totalDmgDone": "73154703.866333",
        "pvp.totalHealingDone": "12140258.135864",
        "pvp.totalKill": "911",
        "pvp.totalVpDmgDone": "126.55975341797",
        "coop.gameWin": "54",
        "coop.gamePlayed": "56",
        "coop.totalBattleTime": "19898130",
        "openWorld.karma": "23281",
        "clan.name": "What Happened In",
        "clan.tag": "VEGAS",
        "clan.cid": "1534",
        "clan.pvpRating": "12452",
        "clan.pveRating": "302751"
      }
    },
    "2026-06-16": {
      "TakenAtUtc": "2026-06-16T23:00:33.8158385Z",
      "Flat": {
        "effRating": "6284.8349609375",
        "nickName": "AlexanToNY",
        "prestigeBonus": "0.45",
        "uid": "1996612",
        "accountRank": "14",
        "pve.gamePlayed": "1784",
        "pve.unlimPve_playerAttackLevel": "15",
        "pve.unlimPve_playerDefenceLevel": "16",
        "pve.unlimPve_missionLevels.planet_war_waves_T1": "19",
        "pve.unlimPve_missionLevels.bigship_building_easy": "7",
        "pve.unlimPve_missionLevels.capture_repairbase_t1": "7",
        "pve.unlimPve_missionLevels.nalnifan_lumen_waves_T1": "19",
        "pve.unlimPve_missionLevels.pve_frozen_station_t2": "6",
        "pve.unlimPve_missionLevels.asteroid_building_t1": "4",
        "pve.unlimPve_missionLevels.pve_jericho_base_t2": "5",
        "pve.unlimPve_missionLevels.bigship_building_2_easy": "8",
        "pve.unlimPve_missionLevels.pve_empfrontier_waves_T1": "3",
        "pve.unlimPve_missionLevels.loot_geostation_normal": "3",
        "pve.unlimPve_missionLevels.piratebay_hard": "2",
        "pve.unlimPve_missionLevels.magnificent_seven": "3",
        "pve.wavePve_maxWave": "12",
        "pvp.gamePlayed": "490",
        "pvp.gameWin": "227",
        "pvp.totalAssists": "2401",
        "pvp.totalBattleTime": "185144052",
        "pvp.totalDeath": "803",
        "pvp.totalDmgDone": "73154703.866333",
        "pvp.totalHealingDone": "12140258.135864",
        "pvp.totalKill": "911",
        "pvp.totalVpDmgDone": "126.55975341797",
        "coop.gameWin": "54",
        "coop.gamePlayed": "56",
        "coop.totalBattleTime": "19898130",
        "openWorld.karma": "23281",
        "clan.name": "What Happened In",
        "clan.tag": "VEGAS",
        "clan.cid": "1534",
        "clan.pvpRating": "11867",
        "clan.pveRating": "291465"
      }
    },
    "2026-06-17": {
      "TakenAtUtc": "2026-06-17T23:00:29.5888914Z",
      "Flat": {
        "effRating": "6284.8349609375",
        "nickName": "AlexanToNY",
        "prestigeBonus": "0.45",
        "uid": "1996612",
        "accountRank": "14",
        "pve.gamePlayed": "1784",
        "pve.unlimPve_playerAttackLevel": "15",
        "pve.unlimPve_playerDefenceLevel": "16",
        "pve.unlimPve_missionLevels.planet_war_waves_T1": "19",
        "pve.unlimPve_missionLevels.bigship_building_easy": "7",
        "pve.unlimPve_missionLevels.capture_repairbase_t1": "7",
        "pve.unlimPve_missionLevels.nalnifan_lumen_waves_T1": "19",
        "pve.unlimPve_missionLevels.pve_frozen_station_t2": "6",
        "pve.unlimPve_missionLevels.asteroid_building_t1": "4",
        "pve.unlimPve_missionLevels.pve_jericho_base_t2": "5",
        "pve.unlimPve_missionLevels.bigship_building_2_easy": "8",
        "pve.unlimPve_missionLevels.pve_empfrontier_waves_T1": "3",
        "pve.unlimPve_missionLevels.loot_geostation_normal": "3",
        "pve.unlimPve_missionLevels.piratebay_hard": "2",
        "pve.unlimPve_missionLevels.magnificent_seven": "3",
        "pve.wavePve_maxWave": "12",
        "pvp.gamePlayed": "490",
        "pvp.gameWin": "227",
        "pvp.totalAssists": "2401",
        "pvp.totalBattleTime": "185144052",
        "pvp.totalDeath": "803",
        "pvp.totalDmgDone": "73154703.866333",
        "pvp.totalHealingDone": "12140258.135864",
        "pvp.totalKill": "911",
        "pvp.totalVpDmgDone": "126.55975341797",
        "coop.gameWin": "54",
        "coop.gamePlayed": "56",
        "coop.totalBattleTime": "19898130",
        "openWorld.karma": "23281",
        "clan.name": "What Happened In",
        "clan.tag": "VEGAS",
        "clan.cid": "1534",
        "clan.pvpRating": "10965",
        "clan.pveRating": "328708"
      }
    },
    "2026-06-18": {
      "TakenAtUtc": "2026-06-18T23:00:34.459641Z",
      "Flat": {
        "effRating": "6284.8349609375",
        "nickName": "AlexanToNY",
        "prestigeBonus": "0.45",
        "uid": "1996612",
        "accountRank": "14",
        "pve.gamePlayed": "1784",
        "pve.unlimPve_playerAttackLevel": "15",
        "pve.unlimPve_playerDefenceLevel": "16",
        "pve.unlimPve_missionLevels.planet_war_waves_T1": "19",
        "pve.unlimPve_missionLevels.bigship_building_easy": "7",
        "pve.unlimPve_missionLevels.capture_repairbase_t1": "7",
        "pve.unlimPve_missionLevels.nalnifan_lumen_waves_T1": "19",
        "pve.unlimPve_missionLevels.pve_frozen_station_t2": "6",
        "pve.unlimPve_missionLevels.asteroid_building_t1": "4",
        "pve.unlimPve_missionLevels.pve_jericho_base_t2": "5",
        "pve.unlimPve_missionLevels.bigship_building_2_easy": "8",
        "pve.unlimPve_missionLevels.pve_empfrontier_waves_T1": "3",
        "pve.unlimPve_missionLevels.loot_geostation_normal": "3",
        "pve.unlimPve_missionLevels.piratebay_hard": "2",
        "pve.unlimPve_missionLevels.magnificent_seven": "3",
        "pve.wavePve_maxWave": "12",
        "pvp.gamePlayed": "490",
        "pvp.gameWin": "227",
        "pvp.totalAssists": "2401",
        "pvp.totalBattleTime": "185144052",
        "pvp.totalDeath": "803",
        "pvp.totalDmgDone": "73154703.866333",
        "pvp.totalHealingDone": "12140258.135864",
        "pvp.totalKill": "911",
        "pvp.totalVpDmgDone": "126.55975341797",
        "coop.gameWin": "54",
        "coop.gamePlayed": "56",
        "coop.totalBattleTime": "19898130",
        "openWorld.karma": "23281",
        "clan.name": "What Happened In",
        "clan.tag": "VEGAS",
        "clan.cid": "1534",
        "clan.pvpRating": "10492",
        "clan.pveRating": "322478"
      }
    },
    "2026-06-19": {
      "TakenAtUtc": "2026-06-19T23:00:30.3163829Z",
      "Flat": {
        "effRating": "6284.8349609375",
        "nickName": "AlexanToNY",
        "prestigeBonus": "0.45",
        "uid": "1996612",
        "accountRank": "14",
        "pve.gamePlayed": "1784",
        "pve.unlimPve_playerAttackLevel": "15",
        "pve.unlimPve_playerDefenceLevel": "16",
        "pve.unlimPve_missionLevels.planet_war_waves_T1": "19",
        "pve.unlimPve_missionLevels.bigship_building_easy": "7",
        "pve.unlimPve_missionLevels.capture_repairbase_t1": "7",
        "pve.unlimPve_missionLevels.nalnifan_lumen_waves_T1": "19",
        "pve.unlimPve_missionLevels.pve_frozen_station_t2": "6",
        "pve.unlimPve_missionLevels.asteroid_building_t1": "4",
        "pve.unlimPve_missionLevels.pve_jericho_base_t2": "5",
        "pve.unlimPve_missionLevels.bigship_building_2_easy": "8",
        "pve.unlimPve_missionLevels.pve_empfrontier_waves_T1": "3",
        "pve.unlimPve_missionLevels.loot_geostation_normal": "3",
        "pve.unlimPve_missionLevels.piratebay_hard": "2",
        "pve.unlimPve_missionLevels.magnificent_seven": "3",
        "pve.wavePve_maxWave": "12",
        "pvp.gamePlayed": "490",
        "pvp.gameWin": "227",
        "pvp.totalAssists": "2401",
        "pvp.totalBattleTime": "185144052",
        "pvp.totalDeath": "803",
        "pvp.totalDmgDone": "73154703.866333",
        "pvp.totalHealingDone": "12140258.135864",
        "pvp.totalKill": "911",
        "pvp.totalVpDmgDone": "126.55975341797",
        "coop.gameWin": "54",
        "coop.gamePlayed": "56",
        "coop.totalBattleTime": "19898130",
        "openWorld.karma": "23281",
        "clan.name": "Notepad Minus",
        "clan.tag": "Minus",
        "clan.cid": "1534",
        "clan.pvpRating": "11202",
        "clan.pveRating": "263241"
      }
    },
    "2026-06-20": {
      "TakenAtUtc": "2026-06-20T23:00:32.9369729Z",
      "Flat": {
        "effRating": "6284.8349609375",
        "nickName": "AlexanToNY",
        "prestigeBonus": "0.45",
        "uid": "1996612",
        "accountRank": "14",
        "pve.gamePlayed": "1784",
        "pve.unlimPve_playerAttackLevel": "15",
        "pve.unlimPve_playerDefenceLevel": "16",
        "pve.unlimPve_missionLevels.planet_war_waves_T1": "19",
        "pve.unlimPve_missionLevels.bigship_building_easy": "7",
        "pve.unlimPve_missionLevels.capture_repairbase_t1": "7",
        "pve.unlimPve_missionLevels.nalnifan_lumen_waves_T1": "19",
        "pve.unlimPve_missionLevels.pve_frozen_station_t2": "6",
        "pve.unlimPve_missionLevels.asteroid_building_t1": "4",
        "pve.unlimPve_missionLevels.pve_jericho_base_t2": "5",
        "pve.unlimPve_missionLevels.bigship_building_2_easy": "8",
        "pve.unlimPve_missionLevels.pve_empfrontier_waves_T1": "3",
        "pve.unlimPve_missionLevels.loot_geostation_normal": "3",
        "pve.unlimPve_missionLevels.piratebay_hard": "2",
        "pve.unlimPve_missionLevels.magnificent_seven": "3",
        "pve.wavePve_maxWave": "12",
        "pvp.gamePlayed": "490",
        "pvp.gameWin": "227",
        "pvp.totalAssists": "2401",
        "pvp.totalBattleTime": "185144052",
        "pvp.totalDeath": "803",
        "pvp.totalDmgDone": "73154703.866333",
        "pvp.totalHealingDone": "12140258.135864",
        "pvp.totalKill": "911",
        "pvp.totalVpDmgDone": "126.55975341797",
        "coop.gameWin": "54",
        "coop.gamePlayed": "56",
        "coop.totalBattleTime": "19898130",
        "openWorld.karma": "23281",
        "clan.name": "Notepad Minus",
        "clan.tag": "Minus",
        "clan.cid": "1534",
        "clan.pvpRating": "10065",
        "clan.pveRating": "365361"
      }
    },
    "2026-06-21": {
      "TakenAtUtc": "2026-06-21T23:00:37.0860249Z",
      "Flat": {
        "effRating": "6284.8349609375",
        "nickName": "AlexanToNY",
        "prestigeBonus": "0.45",
        "uid": "1996612",
        "accountRank": "14",
        "pve.gamePlayed": "1784",
        "pve.unlimPve_playerAttackLevel": "15",
        "pve.unlimPve_playerDefenceLevel": "16",
        "pve.unlimPve_missionLevels.planet_war_waves_T1": "19",
        "pve.unlimPve_missionLevels.bigship_building_easy": "7",
        "pve.unlimPve_missionLevels.capture_repairbase_t1": "7",
        "pve.unlimPve_missionLevels.nalnifan_lumen_waves_T1": "19",
        "pve.unlimPve_missionLevels.pve_frozen_station_t2": "6",
        "pve.unlimPve_missionLevels.asteroid_building_t1": "4",
        "pve.unlimPve_missionLevels.pve_jericho_base_t2": "5",
        "pve.unlimPve_missionLevels.bigship_building_2_easy": "8",
        "pve.unlimPve_missionLevels.pve_empfrontier_waves_T1": "3",
        "pve.unlimPve_missionLevels.loot_geostation_normal": "3",
        "pve.unlimPve_missionLevels.piratebay_hard": "2",
        "pve.unlimPve_missionLevels.magnificent_seven": "3",
        "pve.wavePve_maxWave": "12",
        "pvp.gamePlayed": "490",
        "pvp.gameWin": "227",
        "pvp.totalAssists": "2401",
        "pvp.totalBattleTime": "185144052",
        "pvp.totalDeath": "803",
        "pvp.totalDmgDone": "73154703.866333",
        "pvp.totalHealingDone": "12140258.135864",
        "pvp.totalKill": "911",
        "pvp.totalVpDmgDone": "126.55975341797",
        "coop.gameWin": "54",
        "coop.gamePlayed": "56",
        "coop.totalBattleTime": "19898130",
        "openWorld.karma": "23281",
        "clan.name": "Notepad Minus",
        "clan.tag": "Minus",
        "clan.cid": "1534",
        "clan.pvpRating": "9330",
        "clan.pveRating": "299012"
      }
    },
    "2026-06-22": {
      "TakenAtUtc": "2026-06-22T23:00:30.6531734Z",
      "Flat": {
        "effRating": "6284.8349609375",
        "nickName": "AlexanToNY",
        "prestigeBonus": "0.45",
        "uid": "1996612",
        "accountRank": "14",
        "pve.gamePlayed": "1784",
        "pve.unlimPve_playerAttackLevel": "15",
        "pve.unlimPve_playerDefenceLevel": "16",
        "pve.unlimPve_missionLevels.planet_war_waves_T1": "19",
        "pve.unlimPve_missionLevels.bigship_building_easy": "7",
        "pve.unlimPve_missionLevels.capture_repairbase_t1": "7",
        "pve.unlimPve_missionLevels.nalnifan_lumen_waves_T1": "19",
        "pve.unlimPve_missionLevels.pve_frozen_station_t2": "6",
        "pve.unlimPve_missionLevels.asteroid_building_t1": "4",
        "pve.unlimPve_missionLevels.pve_jericho_base_t2": "5",
        "pve.unlimPve_missionLevels.bigship_building_2_easy": "8",
        "pve.unlimPve_missionLevels.pve_empfrontier_waves_T1": "3",
        "pve.unlimPve_missionLevels.loot_geostation_normal": "3",
        "pve.unlimPve_missionLevels.piratebay_hard": "2",
        "pve.unlimPve_missionLevels.magnificent_seven": "3",
        "pve.wavePve_maxWave": "12",
        "pvp.gamePlayed": "490",
        "pvp.gameWin": "227",
        "pvp.totalAssists": "2401",
        "pvp.totalBattleTime": "185144052",
        "pvp.totalDeath": "803",
        "pvp.totalDmgDone": "73154703.866333",
        "pvp.totalHealingDone": "12140258.135864",
        "pvp.totalKill": "911",
        "pvp.totalVpDmgDone": "126.55975341797",
        "coop.gameWin": "54",
        "coop.gamePlayed": "56",
        "coop.totalBattleTime": "19898130",
        "openWorld.karma": "23281",
        "clan.name": "Notepad Minus",
        "clan.tag": "Minus",
        "clan.cid": "1534",
        "clan.pvpRating": "9558",
        "clan.pveRating": "236415"
      }
    }
  }
}